apng2gif/__init__.py
apng2gif/apng2gif.py
apng2gif-1.0.2.dist-info/LICENSE
apng2gif-1.0.2.dist-info/METADATA
apng2gif-1.0.2.dist-info/WHEEL
apng2gif-1.0.2.dist-info/entry_points.txt
apng2gif-1.0.2.dist-info/top_level.txt
apng2gif-1.0.2.dist-info/RECORD
