Metadata-Version: 2.1
Name: apng2gif
Version: 1.0.2
Summary: convert apng to gif.
Home-page: https://github.com/ThanatosDi/APNG2GIF
Author: ThanatosDi
Author-email: ThanatosDi@kttsite.com
License: UNKNOWN
Platform: UNKNOWN
Classifier: Programming Language :: Python :: 3
Classifier: License :: OSI Approved :: GNU General Public License v3 (GPLv3)
Classifier: Operating System :: OS Independent
Classifier: Development Status :: 4 - Beta
Requires-Dist: apng (==0.3.3)
Requires-Dist: Pillow (>=6.2.0)
